edapdf/__init__.py
edapdf/edapdf.py
edapdf-1.1.dist-info/METADATA
edapdf-1.1.dist-info/WHEEL
edapdf-1.1.dist-info/top_level.txt
edapdf-1.1.dist-info/RECORD
